{
  "$schema": "https://mintlify.com/docs.json",
  "name": "Switchboard",
  "theme": "palm",
  "colors": {
    "primary": "#6366f1",
    "light": "#818cf8",
    "dark": "#4f46e5"
  },
  "navbar": {
    "primary": {
      "type": "github",
      "href": "https://github.com/Aarekaz/switchboard"
    }
  },
  "footer": {
    "socials": {
      "github": "https://github.com/Aarekaz/switchboard"
    }
  },
  "navigation": {
    "tabs": [
      {
        "tab": "Documentation",
        "groups": [
          {
            "group": "Get Started",
            "pages": [
              "introduction",
              "installation",
              "quickstart"
            ]
          },
          {
            "group": "Core Concepts",
            "pages": [
              "concepts/architecture",
              "concepts/platform-adapters",
              "concepts/type-system",
              "concepts/error-handling"
            ]
          },
          {
            "group": "Platform Guides",
            "pages": [
              "platforms/discord",
              "platforms/slack"
            ]
          },
          {
            "group": "Advanced",
            "pages": [
              "advanced/middleware",
              "advanced/custom-adapters",
              "advanced/contributing"
            ]
          }
        ]
      },
      {
        "tab": "API Reference",
        "groups": [
          {
            "group": "Core API",
            "pages": [
              "api/create-bot",
              "api/bot-class",
              "api/configuration"
            ]
          },
          {
            "group": "Platform Adapters",
            "pages": [
              "api/adapters/discord",
              "api/adapters/slack"
            ]
          },
          {
            "group": "Type Reference",
            "pages": [
              "api/types/messages",
              "api/types/events",
              "api/types/channels",
              "api/types/users",
              "api/types/errors"
            ]
          }
        ]
      }
    ]
  }
}
